Metadata-Version: 2.1
Name: insights-analytics-collector
Version: 0.3.2
Summary: Collector Package for Insights for AAP
Home-page: https://github.com/RedHatInsights/insights-analytics-collector/
Author: Martin Slemr
Author-email: mslemr@redhat.com
License: Apache
Classifier: License :: OSI Approved :: Apache Software License
Classifier: Programming Language :: Python
Classifier: Programming Language :: Python :: 3
Classifier: Programming Language :: Python :: 3.6
Classifier: Programming Language :: Python :: 3.7
Classifier: Programming Language :: Python :: 3.8
Classifier: Programming Language :: Python :: 3.9
License-File: LICENSE.md
Requires-Dist: django
Requires-Dist: requests
